vonage/__init__.py
vonage/_internal.py
vonage/account.py
vonage/application.py
vonage/client.py
vonage/errors.py
vonage/meetings.py
vonage/messages.py
vonage/number_insight.py
vonage/numbers.py
vonage/redact.py
vonage/short_codes.py
vonage/sms.py
vonage/ussd.py
vonage/verify.py
vonage/voice.py
vonage/ncco_builder/__init__.py
vonage/ncco_builder/connect_endpoints.py
vonage/ncco_builder/input_types.py
vonage/ncco_builder/ncco.py
vonage/ncco_builder/pay_prompts.py
absolutely_not_the_vonage_python_sdk-4.3.0.dist-info/LICENSE.txt
absolutely_not_the_vonage_python_sdk-4.3.0.dist-info/METADATA
absolutely_not_the_vonage_python_sdk-4.3.0.dist-info/WHEEL
absolutely_not_the_vonage_python_sdk-4.3.0.dist-info/top_level.txt
absolutely_not_the_vonage_python_sdk-4.3.0.dist-info/RECORD
