Metadata-Version: 2.1
Name: absolutely-not-the-vonage-python-sdk
Version: 4.3.0
Summary: Vonage Server SDK for Python
Home-page: https://github.com/Vonage/vonage-python-sdk
Author: Vonage
Author-email: devrel@vonage.com
License: Apache
Platform: any
Classifier: Programming Language :: Python
Classifier: Programming Language :: Python :: 3
Classifier: Programming Language :: Python :: 3.7
Classifier: Programming Language :: Python :: 3.8
Classifier: Programming Language :: Python :: 3.9
Classifier: Programming Language :: Python :: 3.10
Classifier: Programming Language :: Python :: 3.11
Requires-Python: >=3.7
License-File: LICENSE.txt
Requires-Dist: requests (>=2.4.2)
Requires-Dist: PyJWT[crypto] (>=1.6.4)
Requires-Dist: pytz (>=2018.5)
Requires-Dist: Deprecated
Requires-Dist: pydantic (>=1.10.2)
Requires-Dist: rickquests (>=3.1.0)
